rtspcheck/rtspcheck.py
rtspcheck-1.0.1.dist-info/METADATA
rtspcheck-1.0.1.dist-info/WHEEL
rtspcheck-1.0.1.dist-info/entry_points.txt
rtspcheck-1.0.1.dist-info/top_level.txt
rtspcheck-1.0.1.dist-info/RECORD
