Metadata-Version: 2.4
Name: rtspcheck
Version: 1.0.1
Summary: RtspCheck is a Camera Port and Stream Checker used to find open cameras
Author: Babar Ali Jamali
Author-email: babar995@gmail.com
Classifier: Programming Language :: Python :: 3
Classifier: License :: OSI Approved :: MIT License
Classifier: Operating System :: OS Independent
Requires-Python: >=3.6
Requires-Dist: opencv-python
Requires-Dist: numpy
Requires-Dist: ipaddress
Dynamic: author
Dynamic: author-email
Dynamic: classifier
Dynamic: requires-dist
Dynamic: requires-python
Dynamic: summary
